mathlamp_pocket/__init__.py
mathlamp_pocket/base.py
mathlamp_pocket/lines.py
mathlamp_pocket/repl.py
mathlamp_pocket-0.0.2.dist-info/LICENSE
mathlamp_pocket-0.0.2.dist-info/METADATA
mathlamp_pocket-0.0.2.dist-info/WHEEL
mathlamp_pocket-0.0.2.dist-info/RECORD
