Metadata-Version: 2.3
Name: mathlamp-pocket
Version: 0.0.2
Summary: MathLamp strpped down to fit in your pocket
License: MIT
Author: RubberSpring
Author-email: 143825964+RubberSpring@users.noreply.github.com
Requires-Python: >=3.11
Classifier: License :: OSI Approved :: MIT License
Classifier: Programming Language :: Python :: 3
Classifier: Programming Language :: Python :: 3.11
Classifier: Programming Language :: Python :: 3.12
Classifier: Programming Language :: Python :: 3.13
Requires-Dist: lark
